{
  "0xc7efb4076dbe143cbcd98cfaaa929ecfc8f299203dfff63b95ccb6bfe19850fa::swap::lptoken<0x159df6b7689437016108a019fd5bef736bac692b6d4a1f10c941f6fbb9a74ca6::oft::cakeoft, 0x1::aptos_coin::aptoscoin>": {
    "updateDate": "2024-04-01",
    "usdList": [
      {
        "volumeUSD": "367468.8450171372",
        "reserveUSD": "2270034.40084079"
      },
      {
        "volumeUSD": "324816.01582557627",
        "reserveUSD": "2388807.363371025"
      },
      {
        "volumeUSD": "560403.1139908456",
        "reserveUSD": "2458479.986164858"
      },
      {
        "volumeUSD": "404371.56817472144",
        "reserveUSD": "2441649.126946814"
      },
      {
        "volumeUSD": "326134.86165273504",
        "reserveUSD": "2478533.6962185157"
      },
      {
        "volumeUSD": "125732.72830117916",
        "reserveUSD": "1713091.8486227894"
      },
      {
        "volumeUSD": "374504.42832767376",
        "reserveUSD": "1660935.481715649"
      }
    ]
  },
  "0xc7efb4076dbe143cbcd98cfaaa929ecfc8f299203dfff63b95ccb6bfe19850fa::swap::lptoken<0x159df6b7689437016108a019fd5bef736bac692b6d4a1f10c941f6fbb9a74ca6::oft::cakeoft, 0xf22bede237a07e121b56d91a491eb7bcdfd1f5907926a9e58338f964a01b17fa::asset::usdc>": {
    "updateDate": "2024-04-01",
    "usdList": [
      {
        "volumeUSD": "104091.72129054117",
        "reserveUSD": "404417.4958423977"
      },
      {
        "volumeUSD": "58429.91894199608",
        "reserveUSD": "416138.70184772636"
      },
      {
        "volumeUSD": "56666.049029591784",
        "reserveUSD": "398127.9165212574"
      },
      {
        "volumeUSD": "69049.70530518382",
        "reserveUSD": "401420.23788404587"
      },
      {
        "volumeUSD": "46767.45599301662",
        "reserveUSD": "412208.58870957675"
      },
      {
        "volumeUSD": "35826.44478384474",
        "reserveUSD": "416814.3427327883"
      },
      {
        "volumeUSD": "119449.53660194915",
        "reserveUSD": "403687.55433928"
      }
    ]
  },
  "0xc7efb4076dbe143cbcd98cfaaa929ecfc8f299203dfff63b95ccb6bfe19850fa::swap::lptoken<0x159df6b7689437016108a019fd5bef736bac692b6d4a1f10c941f6fbb9a74ca6::oft::cakeoft, 0x8d87a65ba30e09357fa2edea2c80dbac296e5dec2b18287113500b902942929d::celer_coin_manager::usdccoin>": {
    "updateDate": "2024-04-01",
    "usdList": [
      {
        "volumeUSD": "631.9335721537605",
        "reserveUSD": "3252.194923753868"
      },
      {
        "volumeUSD": "410.1202816270788",
        "reserveUSD": "3301.198968261869"
      },
      {
        "volumeUSD": "325.35121225480253",
        "reserveUSD": "3337.0632164281224"
      },
      {
        "volumeUSD": "120.4593875438839",
        "reserveUSD": "3323.4059220028566"
      },
      {
        "volumeUSD": "974.7696815055311",
        "reserveUSD": "3396.9763514273955"
      },
      {
        "volumeUSD": "347.90411813487987",
        "reserveUSD": "3418.2075577164014"
      },
      {
        "volumeUSD": "281.00389077679876",
        "reserveUSD": "3271.898978795602"
      }
    ]
  },
  "0xc7efb4076dbe143cbcd98cfaaa929ecfc8f299203dfff63b95ccb6bfe19850fa::swap::lptoken<0x5e156f1207d0ebfa19a9eeff00d62a282278fb8719f4fab3a586a0a2c0fffbea::coin::t, 0xf22bede237a07e121b56d91a491eb7bcdfd1f5907926a9e58338f964a01b17fa::asset::usdc>": {
    "updateDate": "2024-04-01",
    "usdList": [
      {
        "volumeUSD": "15929.494569471726",
        "reserveUSD": "257804.7224275673"
      },
      {
        "volumeUSD": "13779.07857403822",
        "reserveUSD": "260538.3048610374"
      },
      {
        "volumeUSD": "5711.600464032358",
        "reserveUSD": "260469.38597942534"
      },
      {
        "volumeUSD": "13881.101026364735",
        "reserveUSD": "280496.1445843383"
      },
      {
        "volumeUSD": "28621.330240972384",
        "reserveUSD": "278389.08555695583"
      },
      {
        "volumeUSD": "1815.2281620560864",
        "reserveUSD": "280431.23408855754"
      },
      {
        "volumeUSD": "12668.989912825306",
        "reserveUSD": "287066.3207538677"
      }
    ]
  },
  "0xc7efb4076dbe143cbcd98cfaaa929ecfc8f299203dfff63b95ccb6bfe19850fa::swap::lptoken<0x111ae3e5bc816a5e63c2da97d0aa3886519e0cd5e4b046659fa35796bd11542a::stapt_token::stakedapt, 0xf22bede237a07e121b56d91a491eb7bcdfd1f5907926a9e58338f964a01b17fa::asset::usdc>": {
    "updateDate": "2024-04-01",
    "usdList": [
      {
        "volumeUSD": "29636.29557365926",
        "reserveUSD": "421527.4571230778"
      },
      {
        "volumeUSD": "30168.00617206595",
        "reserveUSD": "430553.6589763125"
      },
      {
        "volumeUSD": "36028.12942164625",
        "reserveUSD": "442819.11267880234"
      },
      {
        "volumeUSD": "32832.72403527655",
        "reserveUSD": "433450.2353412947"
      },
      {
        "volumeUSD": "21485.20550337196",
        "reserveUSD": "866050.9943124311"
      },
      {
        "volumeUSD": "8869.149005559111",
        "reserveUSD": "342354.14835483383"
      },
      {
        "volumeUSD": "32170.47480481844",
        "reserveUSD": "339046.2349183302"
      }
    ]
  },
  "0xc7efb4076dbe143cbcd98cfaaa929ecfc8f299203dfff63b95ccb6bfe19850fa::swap::lptoken<0x111ae3e5bc816a5e63c2da97d0aa3886519e0cd5e4b046659fa35796bd11542a::stapt_token::stakedapt, 0x1::aptos_coin::aptoscoin>": {
    "updateDate": "2024-04-01",
    "usdList": [
      {
        "volumeUSD": "116345.79267193562",
        "reserveUSD": "3317337.1550163818"
      },
      {
        "volumeUSD": "91268.02976831926",
        "reserveUSD": "3475792.8082796335"
      },
      {
        "volumeUSD": "93749.16479104613",
        "reserveUSD": "3687918.3857792662"
      },
      {
        "volumeUSD": "44860.7359658429",
        "reserveUSD": "3629638.4298487343"
      },
      {
        "volumeUSD": "25858.356094211103",
        "reserveUSD": "3535364.320491118"
      },
      {
        "volumeUSD": "16980.246218383785",
        "reserveUSD": "3498343.357041694"
      },
      {
        "volumeUSD": "63922.06218932948",
        "reserveUSD": "3441398.0976430383"
      }
    ]
  },
  "0xc7efb4076dbe143cbcd98cfaaa929ecfc8f299203dfff63b95ccb6bfe19850fa::swap::lptoken<0x1::aptos_coin::aptoscoin, 0xe4ccb6d39136469f376242c31b34d10515c8eaaa38092f804db8e08a8f53c5b2::assets_v1::echocoin002>": {
    "updateDate": "2024-04-01",
    "usdList": [
      {
        "volumeUSD": "588722.33798959",
        "reserveUSD": "2046884.2623267693"
      },
      {
        "volumeUSD": "789466.5685388446",
        "reserveUSD": "2197049.421874894"
      },
      {
        "volumeUSD": "901060.8669272205",
        "reserveUSD": "2087281.3617415875"
      },
      {
        "volumeUSD": "671887.5178971606",
        "reserveUSD": "2044539.3518804144"
      },
      {
        "volumeUSD": "548191.4721306345",
        "reserveUSD": "1858692.9596113807"
      },
      {
        "volumeUSD": "414975.9060831748",
        "reserveUSD": "1795666.2009733976"
      },
      {
        "volumeUSD": "559167.1218214555",
        "reserveUSD": "1899538.433204607"
      }
    ]
  },
  "0xc7efb4076dbe143cbcd98cfaaa929ecfc8f299203dfff63b95ccb6bfe19850fa::swap::lptoken<0x111ae3e5bc816a5e63c2da97d0aa3886519e0cd5e4b046659fa35796bd11542a::amapt_token::amnisapt, 0x1::aptos_coin::aptoscoin>": {
    "updateDate": "2024-04-01",
    "usdList": [
      {
        "volumeUSD": "51203.345416251614",
        "reserveUSD": "3060683.674734358"
      },
      {
        "volumeUSD": "172159.35280732636",
        "reserveUSD": "3193044.6482078"
      },
      {
        "volumeUSD": "47366.94729404505",
        "reserveUSD": "3041355.282241348"
      },
      {
        "volumeUSD": "22685.34006403454",
        "reserveUSD": "2991629.5934270513"
      },
      {
        "volumeUSD": "43999.7182989094",
        "reserveUSD": "2872721.7187094856"
      },
      {
        "volumeUSD": "13984.714496111617",
        "reserveUSD": "2841721.0225918656"
      },
      {
        "volumeUSD": "15882.790807901429",
        "reserveUSD": "2801594.9368900415"
      }
    ]
  },
  "0xc7efb4076dbe143cbcd98cfaaa929ecfc8f299203dfff63b95ccb6bfe19850fa::swap::lptoken<0x1::aptos_coin::aptoscoin, 0x7fd500c11216f0fe3095d0c4b8aa4d64a4e2e04f83758462f2b127255643615::thl_coin::thl>": {
    "updateDate": "2024-04-01",
    "usdList": [
      {
        "volumeUSD": "87954.02138591633",
        "reserveUSD": "122729.29637325669"
      },
      {
        "volumeUSD": "75346.01606564701",
        "reserveUSD": "124002.13504309693"
      },
      {
        "volumeUSD": "80552.7482457698",
        "reserveUSD": "123935.13223162774"
      },
      {
        "volumeUSD": "76554.70610510439",
        "reserveUSD": "105769.35002204336"
      },
      {
        "volumeUSD": "86721.43511991549",
        "reserveUSD": "106071.8128623414"
      },
      {
        "volumeUSD": "52618.284069577276",
        "reserveUSD": "105599.24745752363"
      },
      {
        "volumeUSD": "82622.32841055839",
        "reserveUSD": "109016.57645258932"
      }
    ]
  },
  "0xc7efb4076dbe143cbcd98cfaaa929ecfc8f299203dfff63b95ccb6bfe19850fa::swap::lptoken<0x1::aptos_coin::aptoscoin, 0xfbab9fb68bd2103925317b6a540baa20087b1e7a7a4eb90badee04abb6b5a16f::blt::blt>": {
    "updateDate": "2024-04-01",
    "usdList": [
      {
        "volumeUSD": "4846.075879877011",
        "reserveUSD": "144081.85921681835"
      },
      {
        "volumeUSD": "3948.941627821603",
        "reserveUSD": "142749.7113447925"
      },
      {
        "volumeUSD": "2262.712690095957",
        "reserveUSD": "149507.92629017125"
      },
      {
        "volumeUSD": "3773.6435941098366",
        "reserveUSD": "142377.88814457745"
      },
      {
        "volumeUSD": "3219.178842488067",
        "reserveUSD": "142723.12862250826"
      },
      {
        "volumeUSD": "490.5991077195189",
        "reserveUSD": "128360.70149352656"
      },
      {
        "volumeUSD": "1006.4373086956133",
        "reserveUSD": "126316.96113096437"
      }
    ]
  },
  "0xc7efb4076dbe143cbcd98cfaaa929ecfc8f299203dfff63b95ccb6bfe19850fa::swap::lptoken<0x25a64579760a4c64be0d692327786a6375ec80740152851490cfd0b53604cf95::coin::etern, 0x8d87a65ba30e09357fa2edea2c80dbac296e5dec2b18287113500b902942929d::celer_coin_manager::usdccoin>": {
    "updateDate": "2024-04-01",
    "usdList": [
      {
        "volumeUSD": "22.112594461915762",
        "reserveUSD": "3964.5974575317746"
      },
      {
        "volumeUSD": "0",
        "reserveUSD": "0"
      },
      {
        "volumeUSD": "0",
        "reserveUSD": "0"
      },
      {
        "volumeUSD": "0",
        "reserveUSD": "0"
      },
      {
        "volumeUSD": "0",
        "reserveUSD": "0"
      },
      {
        "volumeUSD": "0",
        "reserveUSD": "0"
      },
      {
        "volumeUSD": "0",
        "reserveUSD": "0"
      }
    ]
  },
  "0xc7efb4076dbe143cbcd98cfaaa929ecfc8f299203dfff63b95ccb6bfe19850fa::swap::lptoken<0x5e156f1207d0ebfa19a9eeff00d62a282278fb8719f4fab3a586a0a2c0fffbea::coin::t, 0x84d7aeef42d38a5ffc3ccef853e1b82e4958659d16a7de736a29c55fbbeb0114::staked_aptos_coin::stakedaptoscoin>": {
    "updateDate": "2024-04-01",
    "usdList": [
      {
        "volumeUSD": "0",
        "reserveUSD": "0"
      },
      {
        "volumeUSD": "0",
        "reserveUSD": "0"
      },
      {
        "volumeUSD": "0",
        "reserveUSD": "0"
      },
      {
        "volumeUSD": "0",
        "reserveUSD": "0"
      },
      {
        "volumeUSD": "0",
        "reserveUSD": "0"
      },
      {
        "volumeUSD": "0",
        "reserveUSD": "0"
      },
      {
        "volumeUSD": "0",
        "reserveUSD": "0"
      }
    ]
  },
  "0xc7efb4076dbe143cbcd98cfaaa929ecfc8f299203dfff63b95ccb6bfe19850fa::swap::lptoken<0x1::aptos_coin::aptoscoin, 0x27fafcc4e39daac97556af8a803dbb52bcb03f0821898dc845ac54225b9793eb::move_coin::movecoin>": {
    "updateDate": "2024-04-01",
    "usdList": [
      {
        "volumeUSD": "8437.252924833758",
        "reserveUSD": "93964.94623314243"
      },
      {
        "volumeUSD": "12528.234076977687",
        "reserveUSD": "93058.61763653357"
      },
      {
        "volumeUSD": "11982.991178310836",
        "reserveUSD": "99948.7346935677"
      },
      {
        "volumeUSD": "40393.4586329898",
        "reserveUSD": "108698.80531843205"
      },
      {
        "volumeUSD": "47615.94769336232",
        "reserveUSD": "116808.08132120283"
      },
      {
        "volumeUSD": "14946.203906592556",
        "reserveUSD": "101787.46835385187"
      },
      {
        "volumeUSD": "73134.2191142389",
        "reserveUSD": "123776.1325321304"
      }
    ]
  },
  "0xc7efb4076dbe143cbcd98cfaaa929ecfc8f299203dfff63b95ccb6bfe19850fa::swap::lptoken<0x1::aptos_coin::aptoscoin, 0xf22bede237a07e121b56d91a491eb7bcdfd1f5907926a9e58338f964a01b17fa::asset::usdc>": {
    "updateDate": "2024-04-01",
    "usdList": [
      {
        "volumeUSD": "1046496.2006695538",
        "reserveUSD": "4530914.016792018"
      },
      {
        "volumeUSD": "997308.9170902877",
        "reserveUSD": "5093842.132411926"
      },
      {
        "volumeUSD": "1841115.4454463813",
        "reserveUSD": "5481930.30673465"
      },
      {
        "volumeUSD": "1436033.1373262468",
        "reserveUSD": "5783093.171378175"
      },
      {
        "volumeUSD": "942576.6797161886",
        "reserveUSD": "5602542.7084785085"
      },
      {
        "volumeUSD": "437067.8248781986",
        "reserveUSD": "5075182.788098728"
      },
      {
        "volumeUSD": "1431880.3119127536",
        "reserveUSD": "4962215.128518717"
      }
    ]
  },
  "0xc7efb4076dbe143cbcd98cfaaa929ecfc8f299203dfff63b95ccb6bfe19850fa::swap::lptoken<0xf22bede237a07e121b56d91a491eb7bcdfd1f5907926a9e58338f964a01b17fa::asset::usdc, 0xf22bede237a07e121b56d91a491eb7bcdfd1f5907926a9e58338f964a01b17fa::asset::weth>": {
    "updateDate": "2024-04-01",
    "usdList": [
      {
        "volumeUSD": "381330.6384161562",
        "reserveUSD": "518799.9962968812"
      },
      {
        "volumeUSD": "223231.96305476734",
        "reserveUSD": "597674.6971379139"
      },
      {
        "volumeUSD": "275572.16711213684",
        "reserveUSD": "584732.5372186606"
      },
      {
        "volumeUSD": "322417.69502559624",
        "reserveUSD": "577134.9915323815"
      },
      {
        "volumeUSD": "205331.52489395504",
        "reserveUSD": "581283.5909996913"
      },
      {
        "volumeUSD": "356106.7360642864",
        "reserveUSD": "591651.4717975801"
      },
      {
        "volumeUSD": "117221.8777445073",
        "reserveUSD": "579998.4479916778"
      }
    ]
  },
  "0xc7efb4076dbe143cbcd98cfaaa929ecfc8f299203dfff63b95ccb6bfe19850fa::swap::lptoken<0xf22bede237a07e121b56d91a491eb7bcdfd1f5907926a9e58338f964a01b17fa::asset::usdc, 0xf22bede237a07e121b56d91a491eb7bcdfd1f5907926a9e58338f964a01b17fa::asset::usdt>": {
    "updateDate": "2024-04-01",
    "usdList": [
      {
        "volumeUSD": "207933.88912255876",
        "reserveUSD": "783521.1571162819"
      },
      {
        "volumeUSD": "75661.72528375695",
        "reserveUSD": "824527.8491004184"
      },
      {
        "volumeUSD": "85158.32606528756",
        "reserveUSD": "871460.5826819476"
      },
      {
        "volumeUSD": "137828.6514423926",
        "reserveUSD": "994312.7172269634"
      },
      {
        "volumeUSD": "105107.16261782926",
        "reserveUSD": "946840.8997807736"
      },
      {
        "volumeUSD": "134273.39108302066",
        "reserveUSD": "846800.2768773357"
      },
      {
        "volumeUSD": "111360.9842875711",
        "reserveUSD": "975228.0728676501"
      }
    ]
  },
  "0xc7efb4076dbe143cbcd98cfaaa929ecfc8f299203dfff63b95ccb6bfe19850fa::swap::lptoken<0x1::aptos_coin::aptoscoin, 0x8d87a65ba30e09357fa2edea2c80dbac296e5dec2b18287113500b902942929d::celer_coin_manager::usdccoin>": {
    "updateDate": "2024-04-01",
    "usdList": [
      {
        "volumeUSD": "4211.864046370621",
        "reserveUSD": "4443.20874682189"
      },
      {
        "volumeUSD": "2475.395713557365",
        "reserveUSD": "4567.742354042031"
      },
      {
        "volumeUSD": "2062.3717959877254",
        "reserveUSD": "4695.191932179053"
      },
      {
        "volumeUSD": "1348.2492955794905",
        "reserveUSD": "4653.940352213183"
      },
      {
        "volumeUSD": "3644.1324192296884",
        "reserveUSD": "4557.995262808261"
      },
      {
        "volumeUSD": "1581.3154109182715",
        "reserveUSD": "4538.131309851182"
      },
      {
        "volumeUSD": "2472.3467046115666",
        "reserveUSD": "4531.292564807551"
      }
    ]
  },
  "0xc7efb4076dbe143cbcd98cfaaa929ecfc8f299203dfff63b95ccb6bfe19850fa::swap::lptoken<0x8d87a65ba30e09357fa2edea2c80dbac296e5dec2b18287113500b902942929d::celer_coin_manager::bnbcoin, 0x8d87a65ba30e09357fa2edea2c80dbac296e5dec2b18287113500b902942929d::celer_coin_manager::usdccoin>": {
    "updateDate": "2024-04-01",
    "usdList": [
      {
        "volumeUSD": "1340.2102198251257",
        "reserveUSD": "32959.94272600445"
      },
      {
        "volumeUSD": "899.821672014486",
        "reserveUSD": "33389.61839374068"
      },
      {
        "volumeUSD": "425.4325827835513",
        "reserveUSD": "33023.54488873272"
      },
      {
        "volumeUSD": "799.3349176223841",
        "reserveUSD": "32852.11119150995"
      },
      {
        "volumeUSD": "1256.7689353057292",
        "reserveUSD": "33440.28798057993"
      },
      {
        "volumeUSD": "130.9392459464063",
        "reserveUSD": "34038.75736242149"
      },
      {
        "volumeUSD": "1198.0813835975307",
        "reserveUSD": "32984.38570690251"
      }
    ]
  },
  "0xc7efb4076dbe143cbcd98cfaaa929ecfc8f299203dfff63b95ccb6bfe19850fa::swap::lptoken<0x8d87a65ba30e09357fa2edea2c80dbac296e5dec2b18287113500b902942929d::celer_coin_manager::usdccoin, 0x8d87a65ba30e09357fa2edea2c80dbac296e5dec2b18287113500b902942929d::celer_coin_manager::wethcoin>": {
    "updateDate": "2024-04-01",
    "usdList": [
      {
        "volumeUSD": "10974.77530984739",
        "reserveUSD": "478119.7984276456"
      },
      {
        "volumeUSD": "14616.330283371619",
        "reserveUSD": "481992.7032800715"
      },
      {
        "volumeUSD": "9947.081098009108",
        "reserveUSD": "486365.44121525926"
      },
      {
        "volumeUSD": "16588.979270743173",
        "reserveUSD": "478036.4328136693"
      },
      {
        "volumeUSD": "6769.78295983323",
        "reserveUSD": "487659.6179074929"
      },
      {
        "volumeUSD": "5294.459342893182",
        "reserveUSD": "487480.85850395745"
      },
      {
        "volumeUSD": "11571.529198069049",
        "reserveUSD": "477924.64007510757"
      }
    ]
  },
  "0xc7efb4076dbe143cbcd98cfaaa929ecfc8f299203dfff63b95ccb6bfe19850fa::swap::lptoken<0x8d87a65ba30e09357fa2edea2c80dbac296e5dec2b18287113500b902942929d::celer_coin_manager::usdccoin, 0x8d87a65ba30e09357fa2edea2c80dbac296e5dec2b18287113500b902942929d::celer_coin_manager::usdtcoin>": {
    "updateDate": "2024-04-01",
    "usdList": [
      {
        "volumeUSD": "1157.7931100477097",
        "reserveUSD": "275326.1175954536"
      },
      {
        "volumeUSD": "1127.6774562945493",
        "reserveUSD": "275216.74934281333"
      },
      {
        "volumeUSD": "867.2518870622716",
        "reserveUSD": "275183.3949515637"
      },
      {
        "volumeUSD": "743.3965843827089",
        "reserveUSD": "272934.26702239097"
      },
      {
        "volumeUSD": "1695.9444974405703",
        "reserveUSD": "275630.7401069665"
      },
      {
        "volumeUSD": "1555.793954996485",
        "reserveUSD": "274425.42591618025"
      },
      {
        "volumeUSD": "587.6989394563554",
        "reserveUSD": "274708.0852982574"
      }
    ]
  },
  "0xc7efb4076dbe143cbcd98cfaaa929ecfc8f299203dfff63b95ccb6bfe19850fa::swap::lptoken<0x1::aptos_coin::aptoscoin, 0x5e156f1207d0ebfa19a9eeff00d62a282278fb8719f4fab3a586a0a2c0fffbea::coin::t>": {
    "updateDate": "2024-04-01",
    "usdList": [
      {
        "volumeUSD": "41647.727154954206",
        "reserveUSD": "179790.87244213483"
      },
      {
        "volumeUSD": "73725.35183112293",
        "reserveUSD": "181464.86777597654"
      },
      {
        "volumeUSD": "101128.15779041019",
        "reserveUSD": "187057.4761938372"
      },
      {
        "volumeUSD": "55282.703533078915",
        "reserveUSD": "185344.94931996"
      },
      {
        "volumeUSD": "83786.13060704741",
        "reserveUSD": "182845.72231235285"
      },
      {
        "volumeUSD": "21396.18191495196",
        "reserveUSD": "174124.2408528556"
      },
      {
        "volumeUSD": "68510.23036144431",
        "reserveUSD": "171873.65072597223"
      }
    ]
  },
  "0xc7efb4076dbe143cbcd98cfaaa929ecfc8f299203dfff63b95ccb6bfe19850fa::swap::lptoken<0x5e156f1207d0ebfa19a9eeff00d62a282278fb8719f4fab3a586a0a2c0fffbea::coin::t, 0xcc8a89c8dce9693d354449f1f73e60e14e347417854f029db5bc8e7454008abb::coin::t>": {
    "updateDate": "2024-04-01",
    "usdList": [
      {
        "volumeUSD": "43154.28319714517",
        "reserveUSD": "866077.6486211476"
      },
      {
        "volumeUSD": "51667.1418675888",
        "reserveUSD": "886795.8480757098"
      },
      {
        "volumeUSD": "55429.394793219035",
        "reserveUSD": "884060.3525377647"
      },
      {
        "volumeUSD": "57654.97998518897",
        "reserveUSD": "872057.4874996913"
      },
      {
        "volumeUSD": "50543.846266290355",
        "reserveUSD": "881421.2906142337"
      },
      {
        "volumeUSD": "24831.780588313006",
        "reserveUSD": "889445.9222856378"
      },
      {
        "volumeUSD": "35195.38557481083",
        "reserveUSD": "871347.7364908562"
      }
    ]
  },
  "0xc7efb4076dbe143cbcd98cfaaa929ecfc8f299203dfff63b95ccb6bfe19850fa::swap::lptoken<0x5e156f1207d0ebfa19a9eeff00d62a282278fb8719f4fab3a586a0a2c0fffbea::coin::t, 0xccc9620d38c4f3991fa68a03ad98ef3735f18d04717cb75d7a1300dd8a7eed75::coin::t>": {
    "updateDate": "2024-04-01",
    "usdList": [
      {
        "volumeUSD": "0",
        "reserveUSD": "0"
      },
      {
        "volumeUSD": "308.2028633502298",
        "reserveUSD": "586.3282993847691"
      },
      {
        "volumeUSD": "0",
        "reserveUSD": "0"
      },
      {
        "volumeUSD": "129.91731641539693",
        "reserveUSD": "590.3462385113153"
      },
      {
        "volumeUSD": "0",
        "reserveUSD": "0"
      },
      {
        "volumeUSD": "0",
        "reserveUSD": "0"
      },
      {
        "volumeUSD": "0",
        "reserveUSD": "0"
      }
    ]
  },
  "0xc7efb4076dbe143cbcd98cfaaa929ecfc8f299203dfff63b95ccb6bfe19850fa::swap::lptoken<0xd11107bdf0d6d7040c6c0bfbdecb6545191fdf13e8d8d259952f53e1713f61b5::staked_coin::stakedaptos, 0xf22bede237a07e121b56d91a491eb7bcdfd1f5907926a9e58338f964a01b17fa::asset::usdc>": {
    "updateDate": "2024-04-01",
    "usdList": [
      {
        "volumeUSD": "5417.199095542233",
        "reserveUSD": "35163.12136928207"
      },
      {
        "volumeUSD": "7118.017741633177",
        "reserveUSD": "35924.65484698414"
      },
      {
        "volumeUSD": "6960.86538194101",
        "reserveUSD": "36592.488280262376"
      },
      {
        "volumeUSD": "6360.895415687356",
        "reserveUSD": "36146.95390268041"
      },
      {
        "volumeUSD": "5768.496250469401",
        "reserveUSD": "35573.95830949595"
      },
      {
        "volumeUSD": "3480.375878144335",
        "reserveUSD": "34927.292362200635"
      },
      {
        "volumeUSD": "7671.697742820409",
        "reserveUSD": "34832.57172383512"
      }
    ]
  }
}
